dhltrack/__init__.py
dhltrack/classes/__init__.py
dhltrack/classes/dhl.py
dhltrack/classes/http.py
dhltrack-0.9.0.dist-info/METADATA
dhltrack-0.9.0.dist-info/WHEEL
dhltrack-0.9.0.dist-info/licenses/LICENSE
dhltrack-0.9.0.dist-info/RECORD
